liblistenbrainz/__init__.py
liblistenbrainz/client.py
liblistenbrainz/errors.py
liblistenbrainz/listen.py
liblistenbrainz/utils.py
liblistenbrainz-0.6.0.dist-info/licenses/LICENSE
liblistenbrainz-0.6.0.dist-info/METADATA
liblistenbrainz-0.6.0.dist-info/WHEEL
liblistenbrainz-0.6.0.dist-info/top_level.txt
liblistenbrainz-0.6.0.dist-info/RECORD
