Metadata-Version: 2.4
Name: liblistenbrainz
Version: 0.6.0
Summary: A simple ListenBrainz client library for Python
Author-email: Param Singh <iliekcomputers@gmail.com>
Project-URL: Homepage, https://github.com/metabrainz/liblistenbrainz
Project-URL: Issues, https://github.com/metabrainz/liblistenbrainz/issues
Project-URL: Documentation, https://liblistenbrainz.readthedocs.io
Project-URL: Releases, https://github.com/metabrainz/liblistenbrainz/releases
Classifier: Programming Language :: Python :: 3
Classifier: License :: OSI Approved :: GNU General Public License v3 (GPLv3)
Classifier: Operating System :: OS Independent
Requires-Python: >=3.8
License-File: LICENSE
Requires-Dist: requests>=2.31.0
Requires-Dist: importlib-metadata>=3.10.0; python_version < "3.10"
Provides-Extra: tests
Requires-Dist: pytest==8.3.4; extra == "tests"
Requires-Dist: pytest-cov>=5.0.0; extra == "tests"
Requires-Dist: requests-mock>=1.12.1; extra == "tests"
Provides-Extra: build
Requires-Dist: build; extra == "build"
Requires-Dist: twine; extra == "build"
Provides-Extra: docs
Requires-Dist: sphinx==3.0.1; extra == "docs"
Dynamic: license-file
